tclg/__init__.py
tclg-0.1.0.dist-info/LICENSE.txt
tclg-0.1.0.dist-info/WHEEL
tclg-0.1.0.dist-info/METADATA
tclg-0.1.0.dist-info/RECORD
