Metadata-Version: 2.1
Name: tclg
Version: 0.1.0
Summary: Utilities, helpers, sugar, etc. for Travis C. LaGrone.
Author: Travis C. LaGrone
Requires-Python: >=3.8,<4.0
Classifier: Programming Language :: Python :: 3
Classifier: Programming Language :: Python :: 3.8
